{".class": "MypyFile", "_fullname": "pint.delegates.txt_defparser.context", "future_import_flags": ["annotations"], "is_partial_stub_package": false, "is_stub": false, "names": {".class": "SymbolTable", "BeginContext": {".class": "SymbolTableNode", "kind": "Gdef", "node": {".class": "TypeInfo", "_promote": [], "abstract_attributes": [], "alt_promote": null, "bases": [{".class": "Instance", "args": [{".class": "AnyType", "missing_import_name": null, "source_any": null, "type_of_any": 4}], "type_ref": "pint._vendor.flexparser.ParsedStatement"}], "dataclass_transform_spec": null, "declared_metaclass": null, "defn": {".class": "ClassDef", "fullname": "pint.delegates.txt_defparser.context.BeginContext", "name": "BeginContext", "type_vars": []}, "deletable_attributes": [], "flags": [], "fullname": "pint.delegates.txt_defparser.context.BeginContext", "has_param_spec_type": false, "metaclass_type": null, "metadata": {"dataclass": {"attributes": [{"alias": null, "column": 4, "has_default": true, "is_in_init": false, "is_init_var": false, "kw_only": false, "line": 52, "name": "start_line", "type": "builtins.int"}, {"alias": null, "column": 4, "has_default": true, "is_in_init": false, "is_init_var": false, "kw_only": false, "line": 53, "name": "start_col", "type": "builtins.int"}, {"alias": null, "column": 4, "has_default": true, "is_in_init": false, "is_init_var": false, "kw_only": false, "line": 55, "name": "end_line", "type": "builtins.int"}, {"alias": null, "column": 4, "has_default": true, "is_in_init": false, "is_init_var": false, "kw_only": false, "line": 56, "name": "end_col", "type": "builtins.int"}, {"alias": null, "column": 4, "has_default": true, "is_in_init": false, "is_init_var": false, "kw_only": false, "line": 58, "name": "raw", "type": "builtins.str"}, {"alias": null, "column": 4, "has_default": false, "is_in_init": true, "is_init_var": false, "kw_only": false, "line": 94, "name": "name", "type": "builtins.str"}, {"alias": null, "column": 4, "has_default": false, "is_in_init": true, "is_init_var": false, "kw_only": false, "line": 95, "name": "aliases", "type": {".class": "Instance", "args": ["builtins.str"], "type_ref": "builtins.tuple"}}, {"alias": null, "column": 4, "has_default": false, "is_in_init": true, "is_init_var": false, "kw_only": false, "line": 96, "name": "defaults", "type": {".class": "Instance", "args": ["builtins.str", "numbers.Number"], "type_ref": "builtins.dict"}}], "frozen": true}, "dataclass_tag": {}}, "module_name": "pint.delegates.txt_defparser.context", "mro": ["pint.delegates.txt_defparser.context.BeginContext", "pint._vendor.flexparser.ParsedStatement", "pint._vendor.flexparser.Statement", "builtins.object"], "names": {".class": "SymbolTable", "__dataclass_fields__": {".class": "SymbolTableNode", "kind": "Mdef", "node": {".class": "Var", "flags": ["is_classvar", "is_ready"], "fullname": "pint.delegates.txt_defparser.context.BeginContext.__dataclass_fields__", "name": "__dataclass_fields__", "type": {".class": "Instance", "args": ["builtins.str", {".class": "Instance", "args": [{".class": "AnyType", "missing_import_name": null, "source_any": null, "type_of_any": 2}], "type_ref": "dataclasses.Field"}], "type_ref": "builtins.dict"}}, "plugin_generated": true}, "__init__": {".class": "SymbolTableNode", "kind": "Mdef", "node": {".class": "FuncDef", "abstract_status": 0, "arg_kinds": [0, 0, 0, 0], "arg_names": ["self", "name", "aliases", "defaults"], "dataclass_transform_spec": null, "flags": [], "fullname": "pint.delegates.txt_defparser.context.BeginContext.__init__", "name": "__init__", "type": {".class": "CallableType", "arg_kinds": [0, 0, 0, 0], "arg_names": ["self", "name", "aliases", "defaults"], "arg_types": ["pint.delegates.txt_defparser.context.BeginContext", "builtins.str", {".class": "Instance", "args": ["builtins.str"], "type_ref": "builtins.tuple"}, {".class": "Instance", "args": ["builtins.str", "numbers.Number"], "type_ref": "builtins.dict"}], "bound_args": [], "def_extras": {}, "fallback": "builtins.function", "from_concatenate": false, "implicit": false, "is_ellipsis_args": false, "name": "__init__ of BeginContext", "ret_type": {".class": "NoneType"}, "type_guard": null, "unpack_kwargs": false, "variables": []}}, "plugin_generated": true}, "__match_args__": {".class": "SymbolTableNode", "kind": "Mdef", "node": {".class": "Var", "flags": ["is_ready", "allow_incompatible_override"], "fullname": "pint.delegates.txt_defparser.context.BeginContext.__match_args__", "name": "__match_args__", "type": {".class": "TupleType", "implicit": false, "items": [{".class": "LiteralType", "fallback": "builtins.str", "value": "name"}, {".class": "LiteralType", "fallback": "builtins.str", "value": "aliases"}, {".class": "LiteralType", "fallback": "builtins.str", "value": "defaults"}], "partial_fallback": {".class": "Instance", "args": [{".class": "AnyType", "missing_import_name": null, "source_any": null, "type_of_any": 6}], "type_ref": "builtins.tuple"}}}, "plugin_generated": true}, "_header_re": {".class": "SymbolTableNode", "kind": "Mdef", "node": {".class": "Var", "flags": ["is_initialized_in_class", "is_inferred", "has_explicit_value"], "fullname": "pint.delegates.txt_defparser.context.BeginContext._header_re", "name": "_header_re", "type": {".class": "Instance", "args": ["builtins.str"], "type_ref": "re.Pattern"}}}, "aliases": {".class": "SymbolTableNode", "implicit": true, "kind": "Mdef", "node": {".class": "Var", "flags": ["is_initialized_in_class", "is_property", "is_ready"], "fullname": "pint.delegates.txt_defparser.context.BeginContext.aliases", "name": "aliases", "type": {".class": "Instance", "args": ["builtins.str"], "type_ref": "builtins.tuple"}}}, "defaults": {".class": "SymbolTableNode", "implicit": true, "kind": "Mdef", "node": {".class": "Var", "flags": ["is_initialized_in_class", "is_property", "is_ready"], "fullname": "pint.delegates.txt_defparser.context.BeginContext.defaults", "name": "defaults", "type": {".class": "Instance", "args": ["builtins.str", "numbers.Number"], "type_ref": "builtins.dict"}}}, "end_col": {".class": "SymbolTableNode", "kind": "Mdef", "node": {".class": "Var", "flags": ["is_property", "is_ready"], "fullname": "pint.delegates.txt_defparser.context.BeginContext.end_col", "name": "end_col", "type": "builtins.int"}}, "end_line": {".class": "SymbolTableNode", "kind": "Mdef", "node": {".class": "Var", "flags": ["is_property", "is_ready"], "fullname": "pint.delegates.txt_defparser.context.BeginContext.end_line", "name": "end_line", "type": "builtins.int"}}, "from_string_and_config": {".class": "SymbolTableNode", "kind": "Mdef", "node": {".class": "Decorator", "func": {".class": "FuncDef", "abstract_status": 0, "arg_kinds": [0, 0, 0], "arg_names": ["cls", "s", "config"], "dataclass_transform_spec": null, "flags": ["is_class", "is_decorated"], "fullname": "pint.delegates.txt_defparser.context.BeginContext.from_string_and_config", "name": "from_string_and_config", "type": {".class": "CallableType", "arg_kinds": [0, 0, 0], "arg_names": ["cls", "s", "config"], "arg_types": [{".class": "TypeType", "item": "pint.delegates.txt_defparser.context.BeginContext"}, "builtins.str", "pint.delegates.base_defparser.ParserConfig"], "bound_args": [], "def_extras": {"first_arg": "cls"}, "fallback": "builtins.function", "from_concatenate": false, "implicit": false, "is_ellipsis_args": false, "name": "from_string_and_config of BeginContext", "ret_type": {".class": "TypeAliasType", "args": ["pint.delegates.txt_defparser.context.BeginContext"], "type_ref": "pint._vendor.flexparser.FromString"}, "type_guard": null, "unpack_kwargs": false, "variables": []}}, "is_overload": false, "var": {".class": "Var", "flags": ["is_initialized_in_class", "is_classmethod", "is_ready", "is_inferred"], "fullname": "pint.delegates.txt_defparser.context.BeginContext.from_string_and_config", "name": "from_string_and_config", "type": {".class": "CallableType", "arg_kinds": [0, 0, 0], "arg_names": ["cls", "s", "config"], "arg_types": [{".class": "TypeType", "item": "pint.delegates.txt_defparser.context.BeginContext"}, "builtins.str", "pint.delegates.base_defparser.ParserConfig"], "bound_args": [], "def_extras": {"first_arg": "cls"}, "fallback": "builtins.function", "from_concatenate": false, "implicit": false, "is_ellipsis_args": false, "name": "from_string_and_config of BeginContext", "ret_type": {".class": "TypeAliasType", "args": ["pint.delegates.txt_defparser.context.BeginContext"], "type_ref": "pint._vendor.flexparser.FromString"}, "type_guard": null, "unpack_kwargs": false, "variables": []}}}}, "name": {".class": "SymbolTableNode", "implicit": true, "kind": "Mdef", "node": {".class": "Var", "flags": ["is_initialized_in_class", "is_property", "is_ready"], "fullname": "pint.delegates.txt_defparser.context.BeginContext.name", "name": "name", "type": "builtins.str"}}, "raw": {".class": "SymbolTableNode", "kind": "Mdef", "node": {".class": "Var", "flags": ["is_property", "is_ready"], "fullname": "pint.delegates.txt_defparser.context.BeginContext.raw", "name": "raw", "type": "builtins.str"}}, "start_col": {".class": "SymbolTableNode", "kind": "Mdef", "node": {".class": "Var", "flags": ["is_property", "is_ready"], "fullname": "pint.delegates.txt_defparser.context.BeginContext.start_col", "name": "start_col", "type": "builtins.int"}}, "start_line": {".class": "SymbolTableNode", "kind": "Mdef", "node": {".class": "Var", "flags": ["is_property", "is_ready"], "fullname": "pint.delegates.txt_defparser.context.BeginContext.start_line", "name": "start_line", "type": "builtins.int"}}}, "self_type": null, "slots": null, "tuple_type": null, "type_vars": [], "typeddict_type": null}}, "BidirectionalRelation": {".class": "SymbolTableNode", "kind": "Gdef", "node": {".class": "TypeInfo", "_promote": [], "abstract_attributes": [], "alt_promote": null, "bases": [{".class": "Instance", "args": [{".class": "AnyType", "missing_import_name": null, "source_any": null, "type_of_any": 4}], "type_ref": "pint._vendor.flexparser.ParsedStatement"}, "pint.facets.context.definitions.BidirectionalRelation", "pint.delegates.txt_defparser.context.Relation"], "dataclass_transform_spec": null, "declared_metaclass": null, "defn": {".class": "ClassDef", "fullname": "pint.delegates.txt_defparser.context.BidirectionalRelation", "name": "BidirectionalRelation", "type_vars": []}, "deletable_attributes": [], "flags": [], "fullname": "pint.delegates.txt_defparser.context.BidirectionalRelation", "has_param_spec_type": false, "metaclass_type": null, "metadata": {"dataclass": {"attributes": [{"alias": null, "column": 4, "has_default": false, "is_in_init": true, "is_init_var": false, "kw_only": false, "line": 31, "name": "src", "type": {".class": "AnyType", "missing_import_name": "pint.facets.context.definitions.UnitsContainer", "source_any": null, "type_of_any": 3}}, {"alias": null, "column": 4, "has_default": false, "is_in_init": true, "is_init_var": false, "kw_only": false, "line": 33, "name": "dst", "type": {".class": "AnyType", "missing_import_name": "pint.facets.context.definitions.UnitsContainer", "source_any": null, "type_of_any": 3}}, {"alias": null, "column": 4, "has_default": false, "is_in_init": true, "is_init_var": false, "kw_only": false, "line": 36, "name": "equation", "type": "builtins.str"}, {"alias": null, "column": 4, "has_default": true, "is_in_init": false, "is_init_var": false, "kw_only": false, "line": 52, "name": "start_line", "type": "builtins.int"}, {"alias": null, "column": 4, "has_default": true, "is_in_init": false, "is_init_var": false, "kw_only": false, "line": 53, "name": "start_col", "type": "builtins.int"}, {"alias": null, "column": 4, "has_default": true, "is_in_init": false, "is_init_var": false, "kw_only": false, "line": 55, "name": "end_line", "type": "builtins.int"}, {"alias": null, "column": 4, "has_default": true, "is_in_init": false, "is_init_var": false, "kw_only": false, "line": 56, "name": "end_col", "type": "builtins.int"}, {"alias": null, "column": 4, "has_default": true, "is_in_init": false, "is_init_var": false, "kw_only": false, "line": 58, "name": "raw", "type": "builtins.str"}], "frozen": true}, "dataclass_tag": {}}, "module_name": "pint.delegates.txt_defparser.context", "mro": ["pint.delegates.txt_defparser.context.BidirectionalRelation", "pint._vendor.flexparser.ParsedStatement", "pint._vendor.flexparser.Statement", "pint.facets.context.definitions.BidirectionalRelation", "pint.delegates.txt_defparser.context.Relation", "pint.facets.context.definitions.Relation", "builtins.object"], "names": {".class": "SymbolTable", "__dataclass_fields__": {".class": "SymbolTableNode", "kind": "Mdef", "node": {".class": "Var", "flags": ["is_classvar", "is_ready"], "fullname": "pint.delegates.txt_defparser.context.BidirectionalRelation.__dataclass_fields__", "name": "__dataclass_fields__", "type": {".class": "Instance", "args": ["builtins.str", {".class": "Instance", "args": [{".class": "AnyType", "missing_import_name": null, "source_any": null, "type_of_any": 2}], "type_ref": "dataclasses.Field"}], "type_ref": "builtins.dict"}}, "plugin_generated": true}, "__init__": {".class": "SymbolTableNode", "kind": "Mdef", "node": {".class": "FuncDef", "abstract_status": 0, "arg_kinds": [0, 0, 0, 0], "arg_names": ["self", "src", "dst", "equation"], "dataclass_transform_spec": null, "flags": [], "fullname": "pint.delegates.txt_defparser.context.BidirectionalRelation.__init__", "name": "__init__", "type": {".class": "CallableType", "arg_kinds": [0, 0, 0, 0], "arg_names": ["self", "src", "dst", "equation"], "arg_types": ["pint.delegates.txt_defparser.context.BidirectionalRelation", {".class": "AnyType", "missing_import_name": "pint.facets.context.definitions.UnitsContainer", "source_any": null, "type_of_any": 3}, {".class": "AnyType", "missing_import_name": "pint.facets.context.definitions.UnitsContainer", "source_any": null, "type_of_any": 3}, "builtins.str"], "bound_args": [], "def_extras": {}, "fallback": "builtins.function", "from_concatenate": false, "implicit": false, "is_ellipsis_args": false, "name": "__init__ of BidirectionalRelation", "ret_type": {".class": "NoneType"}, "type_guard": null, "unpack_kwargs": false, "variables": []}}, "plugin_generated": true}, "__match_args__": {".class": "SymbolTableNode", "kind": "Mdef", "node": {".class": "Var", "flags": ["is_ready", "allow_incompatible_override"], "fullname": "pint.delegates.txt_defparser.context.BidirectionalRelation.__match_args__", "name": "__match_args__", "type": {".class": "TupleType", "implicit": false, "items": [{".class": "LiteralType", "fallback": "builtins.str", "value": "src"}, {".class": "LiteralType", "fallback": "builtins.str", "value": "dst"}, {".class": "LiteralType", "fallback": "builtins.str", "value": "equation"}], "partial_fallback": {".class": "Instance", "args": [{".class": "AnyType", "missing_import_name": null, "source_any": null, "type_of_any": 6}], "type_ref": "builtins.tuple"}}}, "plugin_generated": true}, "dst": {".class": "SymbolTableNode", "kind": "Mdef", "node": {".class": "Var", "flags": ["is_property", "is_ready"], "fullname": "pint.delegates.txt_defparser.context.BidirectionalRelation.dst", "name": "dst", "type": {".class": "AnyType", "missing_import_name": "pint.facets.context.definitions.UnitsContainer", "source_any": null, "type_of_any": 3}}}, "end_col": {".class": "SymbolTableNode", "kind": "Mdef", "node": {".class": "Var", "flags": ["is_property", "is_ready"], "fullname": "pint.delegates.txt_defparser.context.BidirectionalRelation.end_col", "name": "end_col", "type": "builtins.int"}}, "end_line": {".class": "SymbolTableNode", "kind": "Mdef", "node": {".class": "Var", "flags": ["is_property", "is_ready"], "fullname": "pint.delegates.txt_defparser.context.BidirectionalRelation.end_line", "name": "end_line", "type": "builtins.int"}}, "equation": {".class": "SymbolTableNode", "kind": "Mdef", "node": {".class": "Var", "flags": ["is_property", "is_ready"], "fullname": "pint.delegates.txt_defparser.context.BidirectionalRelation.equation", "name": "equation", "type": "builtins.str"}}, "from_string_and_config": {".class": "SymbolTableNode", "kind": "Mdef", "node": {".class": "Decorator", "func": {".class": "FuncDef", "abstract_status": 0, "arg_kinds": [0, 0, 0], "arg_names": ["cls", "s", "config"], "dataclass_transform_spec": null, "flags": ["is_class", "is_decorated"], "fullname": "pint.delegates.txt_defparser.context.BidirectionalRelation.from_string_and_config", "name": "from_string_and_config", "type": {".class": "CallableType", "arg_kinds": [0, 0, 0], "arg_names": ["cls", "s", "config"], "arg_types": [{".class": "TypeType", "item": "pint.delegates.txt_defparser.context.BidirectionalRelation"}, "builtins.str", "pint.delegates.base_defparser.ParserConfig"], "bound_args": [], "def_extras": {"first_arg": "cls"}, "fallback": "builtins.function", "from_concatenate": false, "implicit": false, "is_ellipsis_args": false, "name": "from_string_and_config of BidirectionalRelation", "ret_type": {".class": "TypeAliasType", "args": ["pint.delegates.txt_defparser.context.BidirectionalRelation"], "type_ref": "pint._vendor.flexparser.FromString"}, "type_guard": null, "unpack_kwargs": false, "variables": []}}, "is_overload": false, "var": {".class": "Var", "flags": ["is_initialized_in_class", "is_classmethod", "is_ready", "is_inferred"], "fullname": "pint.delegates.txt_defparser.context.BidirectionalRelation.from_string_and_config", "name": "from_string_and_config", "type": {".class": "CallableType", "arg_kinds": [0, 0, 0], "arg_names": ["cls", "s", "config"], "arg_types": [{".class": "TypeType", "item": "pint.delegates.txt_defparser.context.BidirectionalRelation"}, "builtins.str", "pint.delegates.base_defparser.ParserConfig"], "bound_args": [], "def_extras": {"first_arg": "cls"}, "fallback": "builtins.function", "from_concatenate": false, "implicit": false, "is_ellipsis_args": false, "name": "from_string_and_config of BidirectionalRelation", "ret_type": {".class": "TypeAliasType", "args": ["pint.delegates.txt_defparser.context.BidirectionalRelation"], "type_ref": "pint._vendor.flexparser.FromString"}, "type_guard": null, "unpack_kwargs": false, "variables": []}}}}, "raw": {".class": "SymbolTableNode", "kind": "Mdef", "node": {".class": "Var", "flags": ["is_property", "is_ready"], "fullname": "pint.delegates.txt_defparser.context.BidirectionalRelation.raw", "name": "raw", "type": "builtins.str"}}, "src": {".class": "SymbolTableNode", "kind": "Mdef", "node": {".class": "Var", "flags": ["is_property", "is_ready"], "fullname": "pint.delegates.txt_defparser.context.BidirectionalRelation.src", "name": "src", "type": {".class": "AnyType", "missing_import_name": "pint.facets.context.definitions.UnitsContainer", "source_any": null, "type_of_any": 3}}}, "start_col": {".class": "SymbolTableNode", "kind": "Mdef", "node": {".class": "Var", "flags": ["is_property", "is_ready"], "fullname": "pint.delegates.txt_defparser.context.BidirectionalRelation.start_col", "name": "start_col", "type": "builtins.int"}}, "start_line": {".class": "SymbolTableNode", "kind": "Mdef", "node": {".class": "Var", "flags": ["is_property", "is_ready"], "fullname": "pint.delegates.txt_defparser.context.BidirectionalRelation.start_line", "name": "start_line", "type": "builtins.int"}}}, "self_type": null, "slots": null, "tuple_type": null, "type_vars": [], "typeddict_type": null}}, "ContextDefinition": {".class": "SymbolTableNode", "kind": "Gdef", "node": {".class": "TypeInfo", "_promote": [], "abstract_attributes": [], "alt_promote": null, "bases": ["pint.delegates.txt_defparser.block.DirectiveBlock"], "dataclass_transform_spec": null, "declared_metaclass": null, "defn": {".class": "ClassDef", "fullname": "pint.delegates.txt_defparser.context.ContextDefinition", "name": "ContextDefinition", "type_vars": []}, "deletable_attributes": [], "flags": [], "fullname": "pint.delegates.txt_defparser.context.ContextDefinition", "has_param_spec_type": false, "metaclass_type": null, "metadata": {"dataclass": {"attributes": [{"alias": null, "column": 4, "has_default": false, "is_in_init": true, "is_init_var": false, "kw_only": false, "line": 163, "name": "opening", "type": {".class": "TypeAliasType", "args": ["pint.delegates.txt_defparser.context.BeginContext"], "type_ref": "pint._vendor.flexparser.Single"}}, {"alias": null, "column": 4, "has_default": false, "is_in_init": true, "is_init_var": false, "kw_only": false, "line": 164, "name": "body", "type": {".class": "TypeAliasType", "args": [{".class": "UnionType", "items": ["pint.delegates.txt_defparser.plain.CommentDefinition", "pint.delegates.txt_defparser.context.BidirectionalRelation", "pint.delegates.txt_defparser.context.ForwardRelation", "pint.delegates.txt_defparser.plain.UnitDefinition"]}], "type_ref": "pint._vendor.flexparser.Multi"}}, {"alias": null, "column": 4, "has_default": false, "is_in_init": true, "is_init_var": false, "kw_only": false, "line": 42, "name": "closing", "type": "pint.delegates.txt_defparser.block.EndDirectiveBlock"}], "frozen": true}, "dataclass_tag": {}}, "module_name": "pint.delegates.txt_defparser.context", "mro": ["pint.delegates.txt_defparser.context.ContextDefinition", "pint.delegates.txt_defparser.block.DirectiveBlock", "pint._vendor.flexparser.Block", "builtins.object"], "names": {".class": "SymbolTable", "__dataclass_fields__": {".class": "SymbolTableNode", "kind": "Mdef", "node": {".class": "Var", "flags": ["is_classvar", "is_ready"], "fullname": "pint.delegates.txt_defparser.context.ContextDefinition.__dataclass_fields__", "name": "__dataclass_fields__", "type": {".class": "Instance", "args": ["builtins.str", {".class": "Instance", "args": [{".class": "AnyType", "missing_import_name": null, "source_any": null, "type_of_any": 2}], "type_ref": "dataclasses.Field"}], "type_ref": "builtins.dict"}}, "plugin_generated": true}, "__init__": {".class": "SymbolTableNode", "kind": "Mdef", "node": {".class": "FuncDef", "abstract_status": 0, "arg_kinds": [0, 0, 0, 0], "arg_names": ["self", "opening", "body", "closing"], "dataclass_transform_spec": null, "flags": [], "fullname": "pint.delegates.txt_defparser.context.ContextDefinition.__init__", "name": "__init__", "type": {".class": "CallableType", "arg_kinds": [0, 0, 0, 0], "arg_names": ["self", "opening", "body", "closing"], "arg_types": ["pint.delegates.txt_defparser.context.ContextDefinition", {".class": "TypeAliasType", "args": ["pint.delegates.txt_defparser.context.BeginContext"], "type_ref": "pint._vendor.flexparser.Single"}, {".class": "TypeAliasType", "args": [{".class": "UnionType", "items": ["pint.delegates.txt_defparser.plain.CommentDefinition", "pint.delegates.txt_defparser.context.BidirectionalRelation", "pint.delegates.txt_defparser.context.ForwardRelation", "pint.delegates.txt_defparser.plain.UnitDefinition"]}], "type_ref": "pint._vendor.flexparser.Multi"}, "pint.delegates.txt_defparser.block.EndDirectiveBlock"], "bound_args": [], "def_extras": {}, "fallback": "builtins.function", "from_concatenate": false, "implicit": false, "is_ellipsis_args": false, "name": "__init__ of ContextDefinition", "ret_type": {".class": "NoneType"}, "type_guard": null, "unpack_kwargs": false, "variables": []}}, "plugin_generated": true}, "__match_args__": {".class": "SymbolTableNode", "kind": "Mdef", "node": {".class": "Var", "flags": ["is_ready", "allow_incompatible_override"], "fullname": "pint.delegates.txt_defparser.context.ContextDefinition.__match_args__", "name": "__match_args__", "type": {".class": "TupleType", "implicit": false, "items": [{".class": "LiteralType", "fallback": "builtins.str", "value": "opening"}, {".class": "LiteralType", "fallback": "builtins.str", "value": "body"}, {".class": "LiteralType", "fallback": "builtins.str", "value": "closing"}], "partial_fallback": {".class": "Instance", "args": [{".class": "AnyType", "missing_import_name": null, "source_any": null, "type_of_any": 6}], "type_ref": "builtins.tuple"}}}, "plugin_generated": true}, "aliases": {".class": "SymbolTableNode", "kind": "Mdef", "node": {".class": "Decorator", "func": {".class": "FuncDef", "abstract_status": 0, "arg_kinds": [0], "arg_names": ["self"], "dataclass_transform_spec": null, "flags": ["is_property", "is_decorated"], "fullname": "pint.delegates.txt_defparser.context.ContextDefinition.aliases", "name": "aliases", "type": null}, "is_overload": false, "var": {".class": "Var", "flags": ["is_initialized_in_class", "is_property", "is_ready", "is_inferred"], "fullname": "pint.delegates.txt_defparser.context.ContextDefinition.aliases", "name": "aliases", "type": {".class": "CallableType", "arg_kinds": [0], "arg_names": ["self"], "arg_types": ["pint.delegates.txt_defparser.context.ContextDefinition"], "bound_args": [], "def_extras": {"first_arg": "self"}, "fallback": "builtins.function", "from_concatenate": false, "implicit": true, "is_ellipsis_args": false, "name": "aliases of ContextDefinition", "ret_type": {".class": "AnyType", "missing_import_name": null, "source_any": null, "type_of_any": 1}, "type_guard": null, "unpack_kwargs": false, "variables": []}}}}, "body": {".class": "SymbolTableNode", "implicit": true, "kind": "Mdef", "node": {".class": "Var", "flags": ["is_initialized_in_class", "is_property", "is_ready"], "fullname": "pint.delegates.txt_defparser.context.ContextDefinition.body", "name": "body", "type": {".class": "TypeAliasType", "args": [{".class": "UnionType", "items": ["pint.delegates.txt_defparser.plain.CommentDefinition", "pint.delegates.txt_defparser.context.BidirectionalRelation", "pint.delegates.txt_defparser.context.ForwardRelation", "pint.delegates.txt_defparser.plain.UnitDefinition"]}], "type_ref": "pint._vendor.flexparser.Multi"}}}, "closing": {".class": "SymbolTableNode", "kind": "Mdef", "node": {".class": "Var", "flags": ["is_property", "is_ready"], "fullname": "pint.delegates.txt_defparser.context.ContextDefinition.closing", "name": "closing", "type": "pint.delegates.txt_defparser.block.EndDirectiveBlock"}}, "defaults": {".class": "SymbolTableNode", "kind": "Mdef", "node": {".class": "Decorator", "func": {".class": "FuncDef", "abstract_status": 0, "arg_kinds": [0], "arg_names": ["self"], "dataclass_transform_spec": null, "flags": ["is_property", "is_decorated"], "fullname": "pint.delegates.txt_defparser.context.ContextDefinition.defaults", "name": "defaults", "type": null}, "is_overload": false, "var": {".class": "Var", "flags": ["is_initialized_in_class", "is_property", "is_ready", "is_inferred"], "fullname": "pint.delegates.txt_defparser.context.ContextDefinition.defaults", "name": "defaults", "type": {".class": "CallableType", "arg_kinds": [0], "arg_names": ["self"], "arg_types": ["pint.delegates.txt_defparser.context.ContextDefinition"], "bound_args": [], "def_extras": {"first_arg": "self"}, "fallback": "builtins.function", "from_concatenate": false, "implicit": true, "is_ellipsis_args": false, "name": "defaults of ContextDefinition", "ret_type": {".class": "AnyType", "missing_import_name": null, "source_any": null, "type_of_any": 1}, "type_guard": null, "unpack_kwargs": false, "variables": []}}}}, "derive_definition": {".class": "SymbolTableNode", "kind": "Mdef", "node": {".class": "FuncDef", "abstract_status": 0, "arg_kinds": [0], "arg_names": ["self"], "dataclass_transform_spec": null, "flags": [], "fullname": "pint.delegates.txt_defparser.context.ContextDefinition.derive_definition", "name": "derive_definition", "type": null}}, "name": {".class": "SymbolTableNode", "kind": "Mdef", "node": {".class": "Decorator", "func": {".class": "FuncDef", "abstract_status": 0, "arg_kinds": [0], "arg_names": ["self"], "dataclass_transform_spec": null, "flags": ["is_property", "is_decorated"], "fullname": "pint.delegates.txt_defparser.context.ContextDefinition.name", "name": "name", "type": null}, "is_overload": false, "var": {".class": "Var", "flags": ["is_initialized_in_class", "is_property", "is_ready", "is_inferred"], "fullname": "pint.delegates.txt_defparser.context.ContextDefinition.name", "name": "name", "type": {".class": "CallableType", "arg_kinds": [0], "arg_names": ["self"], "arg_types": ["pint.delegates.txt_defparser.context.ContextDefinition"], "bound_args": [], "def_extras": {"first_arg": "self"}, "fallback": "builtins.function", "from_concatenate": false, "implicit": true, "is_ellipsis_args": false, "name": "name of ContextDefinition", "ret_type": {".class": "AnyType", "missing_import_name": null, "source_any": null, "type_of_any": 1}, "type_guard": null, "unpack_kwargs": false, "variables": []}}}}, "opening": {".class": "SymbolTableNode", "implicit": true, "kind": "Mdef", "node": {".class": "Var", "flags": ["is_initialized_in_class", "is_property", "is_ready"], "fullname": "pint.delegates.txt_defparser.context.ContextDefinition.opening", "name": "opening", "type": {".class": "TypeAliasType", "args": ["pint.delegates.txt_defparser.context.BeginContext"], "type_ref": "pint._vendor.flexparser.Single"}}}, "redefinitions": {".class": "SymbolTableNode", "kind": "Mdef", "node": {".class": "Decorator", "func": {".class": "FuncDef", "abstract_status": 0, "arg_kinds": [0], "arg_names": ["self"], "dataclass_transform_spec": null, "flags": ["is_property", "is_decorated"], "fullname": "pint.delegates.txt_defparser.context.ContextDefinition.redefinitions", "name": "redefinitions", "type": null}, "is_overload": false, "var": {".class": "Var", "flags": ["is_initialized_in_class", "is_property", "is_ready", "is_inferred"], "fullname": "pint.delegates.txt_defparser.context.ContextDefinition.redefinitions", "name": "redefinitions", "type": {".class": "CallableType", "arg_kinds": [0], "arg_names": ["self"], "arg_types": ["pint.delegates.txt_defparser.context.ContextDefinition"], "bound_args": [], "def_extras": {"first_arg": "self"}, "fallback": "builtins.function", "from_concatenate": false, "implicit": true, "is_ellipsis_args": false, "name": "redefinitions of ContextDefinition", "ret_type": {".class": "AnyType", "missing_import_name": null, "source_any": null, "type_of_any": 1}, "type_guard": null, "unpack_kwargs": false, "variables": []}}}}, "relations": {".class": "SymbolTableNode", "kind": "Mdef", "node": {".class": "Decorator", "func": {".class": "FuncDef", "abstract_status": 0, "arg_kinds": [0], "arg_names": ["self"], "dataclass_transform_spec": null, "flags": ["is_property", "is_decorated"], "fullname": "pint.delegates.txt_defparser.context.ContextDefinition.relations", "name": "relations", "type": null}, "is_overload": false, "var": {".class": "Var", "flags": ["is_initialized_in_class", "is_property", "is_ready", "is_inferred"], "fullname": "pint.delegates.txt_defparser.context.ContextDefinition.relations", "name": "relations", "type": {".class": "CallableType", "arg_kinds": [0], "arg_names": ["self"], "arg_types": ["pint.delegates.txt_defparser.context.ContextDefinition"], "bound_args": [], "def_extras": {"first_arg": "self"}, "fallback": "builtins.function", "from_concatenate": false, "implicit": true, "is_ellipsis_args": false, "name": "relations of ContextDefinition", "ret_type": {".class": "AnyType", "missing_import_name": null, "source_any": null, "type_of_any": 1}, "type_guard": null, "unpack_kwargs": false, "variables": []}}}}}, "self_type": null, "slots": null, "tuple_type": null, "type_vars": [], "typeddict_type": null}}, "Dict": {".class": "SymbolTableNode", "cross_ref": "typing.Dict", "kind": "Gdef"}, "ForwardRelation": {".class": "SymbolTableNode", "kind": "Gdef", "node": {".class": "TypeInfo", "_promote": [], "abstract_attributes": [], "alt_promote": null, "bases": [{".class": "Instance", "args": [{".class": "AnyType", "missing_import_name": null, "source_any": null, "type_of_any": 4}], "type_ref": "pint._vendor.flexparser.ParsedStatement"}, "pint.facets.context.definitions.ForwardRelation", "pint.delegates.txt_defparser.context.Relation"], "dataclass_transform_spec": null, "declared_metaclass": null, "defn": {".class": "ClassDef", "fullname": "pint.delegates.txt_defparser.context.ForwardRelation", "name": "ForwardRelation", "type_vars": []}, "deletable_attributes": [], "flags": [], "fullname": "pint.delegates.txt_defparser.context.ForwardRelation", "has_param_spec_type": false, "metaclass_type": null, "metadata": {"dataclass": {"attributes": [{"alias": null, "column": 4, "has_default": false, "is_in_init": true, "is_init_var": false, "kw_only": false, "line": 31, "name": "src", "type": {".class": "AnyType", "missing_import_name": "pint.facets.context.definitions.UnitsContainer", "source_any": null, "type_of_any": 3}}, {"alias": null, "column": 4, "has_default": false, "is_in_init": true, "is_init_var": false, "kw_only": false, "line": 33, "name": "dst", "type": {".class": "AnyType", "missing_import_name": "pint.facets.context.definitions.UnitsContainer", "source_any": null, "type_of_any": 3}}, {"alias": null, "column": 4, "has_default": false, "is_in_init": true, "is_init_var": false, "kw_only": false, "line": 36, "name": "equation", "type": "builtins.str"}, {"alias": null, "column": 4, "has_default": true, "is_in_init": false, "is_init_var": false, "kw_only": false, "line": 52, "name": "start_line", "type": "builtins.int"}, {"alias": null, "column": 4, "has_default": true, "is_in_init": false, "is_init_var": false, "kw_only": false, "line": 53, "name": "start_col", "type": "builtins.int"}, {"alias": null, "column": 4, "has_default": true, "is_in_init": false, "is_init_var": false, "kw_only": false, "line": 55, "name": "end_line", "type": "builtins.int"}, {"alias": null, "column": 4, "has_default": true, "is_in_init": false, "is_init_var": false, "kw_only": false, "line": 56, "name": "end_col", "type": "builtins.int"}, {"alias": null, "column": 4, "has_default": true, "is_in_init": false, "is_init_var": false, "kw_only": false, "line": 58, "name": "raw", "type": "builtins.str"}], "frozen": true}, "dataclass_tag": {}}, "module_name": "pint.delegates.txt_defparser.context", "mro": ["pint.delegates.txt_defparser.context.ForwardRelation", "pint._vendor.flexparser.ParsedStatement", "pint._vendor.flexparser.Statement", "pint.facets.context.definitions.ForwardRelation", "pint.delegates.txt_defparser.context.Relation", "pint.facets.context.definitions.Relation", "builtins.object"], "names": {".class": "SymbolTable", "__dataclass_fields__": {".class": "SymbolTableNode", "kind": "Mdef", "node": {".class": "Var", "flags": ["is_classvar", "is_ready"], "fullname": "pint.delegates.txt_defparser.context.ForwardRelation.__dataclass_fields__", "name": "__dataclass_fields__", "type": {".class": "Instance", "args": ["builtins.str", {".class": "Instance", "args": [{".class": "AnyType", "missing_import_name": null, "source_any": null, "type_of_any": 2}], "type_ref": "dataclasses.Field"}], "type_ref": "builtins.dict"}}, "plugin_generated": true}, "__init__": {".class": "SymbolTableNode", "kind": "Mdef", "node": {".class": "FuncDef", "abstract_status": 0, "arg_kinds": [0, 0, 0, 0], "arg_names": ["self", "src", "dst", "equation"], "dataclass_transform_spec": null, "flags": [], "fullname": "pint.delegates.txt_defparser.context.ForwardRelation.__init__", "name": "__init__", "type": {".class": "CallableType", "arg_kinds": [0, 0, 0, 0], "arg_names": ["self", "src", "dst", "equation"], "arg_types": ["pint.delegates.txt_defparser.context.ForwardRelation", {".class": "AnyType", "missing_import_name": "pint.facets.context.definitions.UnitsContainer", "source_any": null, "type_of_any": 3}, {".class": "AnyType", "missing_import_name": "pint.facets.context.definitions.UnitsContainer", "source_any": null, "type_of_any": 3}, "builtins.str"], "bound_args": [], "def_extras": {}, "fallback": "builtins.function", "from_concatenate": false, "implicit": false, "is_ellipsis_args": false, "name": "__init__ of ForwardRelation", "ret_type": {".class": "NoneType"}, "type_guard": null, "unpack_kwargs": false, "variables": []}}, "plugin_generated": true}, "__match_args__": {".class": "SymbolTableNode", "kind": "Mdef", "node": {".class": "Var", "flags": ["is_ready", "allow_incompatible_override"], "fullname": "pint.delegates.txt_defparser.context.ForwardRelation.__match_args__", "name": "__match_args__", "type": {".class": "TupleType", "implicit": false, "items": [{".class": "LiteralType", "fallback": "builtins.str", "value": "src"}, {".class": "LiteralType", "fallback": "builtins.str", "value": "dst"}, {".class": "LiteralType", "fallback": "builtins.str", "value": "equation"}], "partial_fallback": {".class": "Instance", "args": [{".class": "AnyType", "missing_import_name": null, "source_any": null, "type_of_any": 6}], "type_ref": "builtins.tuple"}}}, "plugin_generated": true}, "dst": {".class": "SymbolTableNode", "kind": "Mdef", "node": {".class": "Var", "flags": ["is_property", "is_ready"], "fullname": "pint.delegates.txt_defparser.context.ForwardRelation.dst", "name": "dst", "type": {".class": "AnyType", "missing_import_name": "pint.facets.context.definitions.UnitsContainer", "source_any": null, "type_of_any": 3}}}, "end_col": {".class": "SymbolTableNode", "kind": "Mdef", "node": {".class": "Var", "flags": ["is_property", "is_ready"], "fullname": "pint.delegates.txt_defparser.context.ForwardRelation.end_col", "name": "end_col", "type": "builtins.int"}}, "end_line": {".class": "SymbolTableNode", "kind": "Mdef", "node": {".class": "Var", "flags": ["is_property", "is_ready"], "fullname": "pint.delegates.txt_defparser.context.ForwardRelation.end_line", "name": "end_line", "type": "builtins.int"}}, "equation": {".class": "SymbolTableNode", "kind": "Mdef", "node": {".class": "Var", "flags": ["is_property", "is_ready"], "fullname": "pint.delegates.txt_defparser.context.ForwardRelation.equation", "name": "equation", "type": "builtins.str"}}, "from_string_and_config": {".class": "SymbolTableNode", "kind": "Mdef", "node": {".class": "Decorator", "func": {".class": "FuncDef", "abstract_status": 0, "arg_kinds": [0, 0, 0], "arg_names": ["cls", "s", "config"], "dataclass_transform_spec": null, "flags": ["is_class", "is_decorated"], "fullname": "pint.delegates.txt_defparser.context.ForwardRelation.from_string_and_config", "name": "from_string_and_config", "type": {".class": "CallableType", "arg_kinds": [0, 0, 0], "arg_names": ["cls", "s", "config"], "arg_types": [{".class": "TypeType", "item": "pint.delegates.txt_defparser.context.ForwardRelation"}, "builtins.str", "pint.delegates.base_defparser.ParserConfig"], "bound_args": [], "def_extras": {"first_arg": "cls"}, "fallback": "builtins.function", "from_concatenate": false, "implicit": false, "is_ellipsis_args": false, "name": "from_string_and_config of ForwardRelation", "ret_type": {".class": "TypeAliasType", "args": ["pint.delegates.txt_defparser.context.ForwardRelation"], "type_ref": "pint._vendor.flexparser.FromString"}, "type_guard": null, "unpack_kwargs": false, "variables": []}}, "is_overload": false, "var": {".class": "Var", "flags": ["is_initialized_in_class", "is_classmethod", "is_ready", "is_inferred"], "fullname": "pint.delegates.txt_defparser.context.ForwardRelation.from_string_and_config", "name": "from_string_and_config", "type": {".class": "CallableType", "arg_kinds": [0, 0, 0], "arg_names": ["cls", "s", "config"], "arg_types": [{".class": "TypeType", "item": "pint.delegates.txt_defparser.context.ForwardRelation"}, "builtins.str", "pint.delegates.base_defparser.ParserConfig"], "bound_args": [], "def_extras": {"first_arg": "cls"}, "fallback": "builtins.function", "from_concatenate": false, "implicit": false, "is_ellipsis_args": false, "name": "from_string_and_config of ForwardRelation", "ret_type": {".class": "TypeAliasType", "args": ["pint.delegates.txt_defparser.context.ForwardRelation"], "type_ref": "pint._vendor.flexparser.FromString"}, "type_guard": null, "unpack_kwargs": false, "variables": []}}}}, "raw": {".class": "SymbolTableNode", "kind": "Mdef", "node": {".class": "Var", "flags": ["is_property", "is_ready"], "fullname": "pint.delegates.txt_defparser.context.ForwardRelation.raw", "name": "raw", "type": "builtins.str"}}, "src": {".class": "SymbolTableNode", "kind": "Mdef", "node": {".class": "Var", "flags": ["is_property", "is_ready"], "fullname": "pint.delegates.txt_defparser.context.ForwardRelation.src", "name": "src", "type": {".class": "AnyType", "missing_import_name": "pint.facets.context.definitions.UnitsContainer", "source_any": null, "type_of_any": 3}}}, "start_col": {".class": "SymbolTableNode", "kind": "Mdef", "node": {".class": "Var", "flags": ["is_property", "is_ready"], "fullname": "pint.delegates.txt_defparser.context.ForwardRelation.start_col", "name": "start_col", "type": "builtins.int"}}, "start_line": {".class": "SymbolTableNode", "kind": "Mdef", "node": {".class": "Var", "flags": ["is_property", "is_ready"], "fullname": "pint.delegates.txt_defparser.context.ForwardRelation.start_line", "name": "start_line", "type": "builtins.int"}}}, "self_type": null, "slots": null, "tuple_type": null, "type_vars": [], "typeddict_type": null}}, "ParserConfig": {".class": "SymbolTableNode", "cross_ref": "pint.delegates.base_defparser.ParserConfig", "kind": "Gdef"}, "Relation": {".class": "SymbolTableNode", "kind": "Gdef", "node": {".class": "TypeInfo", "_promote": [], "abstract_attributes": [], "alt_promote": null, "bases": ["pint.facets.context.definitions.Relation"], "dataclass_transform_spec": null, "declared_metaclass": null, "defn": {".class": "ClassDef", "fullname": "pint.delegates.txt_defparser.context.Relation", "name": "Relation", "type_vars": []}, "deletable_attributes": [], "flags": [], "fullname": "pint.delegates.txt_defparser.context.Relation", "has_param_spec_type": false, "metaclass_type": null, "metadata": {"dataclass": {"attributes": [{"alias": null, "column": 4, "has_default": false, "is_in_init": true, "is_init_var": false, "kw_only": false, "line": 31, "name": "src", "type": {".class": "AnyType", "missing_import_name": "pint.facets.context.definitions.UnitsContainer", "source_any": null, "type_of_any": 3}}, {"alias": null, "column": 4, "has_default": false, "is_in_init": true, "is_init_var": false, "kw_only": false, "line": 33, "name": "dst", "type": {".class": "AnyType", "missing_import_name": "pint.facets.context.definitions.UnitsContainer", "source_any": null, "type_of_any": 3}}, {"alias": null, "column": 4, "has_default": false, "is_in_init": true, "is_init_var": false, "kw_only": false, "line": 36, "name": "equation", "type": "builtins.str"}], "frozen": true}, "dataclass_tag": {}}, "module_name": "pint.delegates.txt_defparser.context", "mro": ["pint.delegates.txt_defparser.context.Relation", "pint.facets.context.definitions.Relation", "builtins.object"], "names": {".class": "SymbolTable", "__dataclass_fields__": {".class": "SymbolTableNode", "kind": "Mdef", "node": {".class": "Var", "flags": ["is_classvar", "is_ready"], "fullname": "pint.delegates.txt_defparser.context.Relation.__dataclass_fields__", "name": "__dataclass_fields__", "type": {".class": "Instance", "args": ["builtins.str", {".class": "Instance", "args": [{".class": "AnyType", "missing_import_name": null, "source_any": null, "type_of_any": 2}], "type_ref": "dataclasses.Field"}], "type_ref": "builtins.dict"}}, "plugin_generated": true}, "__init__": {".class": "SymbolTableNode", "kind": "Mdef", "node": {".class": "FuncDef", "abstract_status": 0, "arg_kinds": [0, 0, 0, 0], "arg_names": ["self", "src", "dst", "equation"], "dataclass_transform_spec": null, "flags": [], "fullname": "pint.delegates.txt_defparser.context.Relation.__init__", "name": "__init__", "type": {".class": "CallableType", "arg_kinds": [0, 0, 0, 0], "arg_names": ["self", "src", "dst", "equation"], "arg_types": ["pint.delegates.txt_defparser.context.Relation", {".class": "AnyType", "missing_import_name": "pint.facets.context.definitions.UnitsContainer", "source_any": null, "type_of_any": 3}, {".class": "AnyType", "missing_import_name": "pint.facets.context.definitions.UnitsContainer", "source_any": null, "type_of_any": 3}, "builtins.str"], "bound_args": [], "def_extras": {}, "fallback": "builtins.function", "from_concatenate": false, "implicit": false, "is_ellipsis_args": false, "name": "__init__ of Relation", "ret_type": {".class": "NoneType"}, "type_guard": null, "unpack_kwargs": false, "variables": []}}, "plugin_generated": true}, "__match_args__": {".class": "SymbolTableNode", "kind": "Mdef", "node": {".class": "Var", "flags": ["is_ready", "allow_incompatible_override"], "fullname": "pint.delegates.txt_defparser.context.Relation.__match_args__", "name": "__match_args__", "type": {".class": "TupleType", "implicit": false, "items": [{".class": "LiteralType", "fallback": "builtins.str", "value": "src"}, {".class": "LiteralType", "fallback": "builtins.str", "value": "dst"}, {".class": "LiteralType", "fallback": "builtins.str", "value": "equation"}], "partial_fallback": {".class": "Instance", "args": [{".class": "AnyType", "missing_import_name": null, "source_any": null, "type_of_any": 6}], "type_ref": "builtins.tuple"}}}, "plugin_generated": true}, "_from_string_and_context_sep": {".class": "SymbolTableNode", "kind": "Mdef", "node": {".class": "Decorator", "func": {".class": "FuncDef", "abstract_status": 0, "arg_kinds": [0, 0, 0, 0], "arg_names": ["cls", "s", "config", "separator"], "dataclass_transform_spec": null, "flags": ["is_class", "is_decorated"], "fullname": "pint.delegates.txt_defparser.context.Relation._from_string_and_context_sep", "name": "_from_string_and_context_sep", "type": {".class": "CallableType", "arg_kinds": [0, 0, 0, 0], "arg_names": ["cls", "s", "config", "separator"], "arg_types": [{".class": "TypeType", "item": "pint.delegates.txt_defparser.context.Relation"}, "builtins.str", "pint.delegates.base_defparser.ParserConfig", "builtins.str"], "bound_args": [], "def_extras": {"first_arg": "cls"}, "fallback": "builtins.function", "from_concatenate": false, "implicit": false, "is_ellipsis_args": false, "name": "_from_string_and_context_sep of Relation", "ret_type": {".class": "TypeAliasType", "args": ["pint.delegates.txt_defparser.context.Relation"], "type_ref": "pint._vendor.flexparser.FromString"}, "type_guard": null, "unpack_kwargs": false, "variables": []}}, "is_overload": false, "var": {".class": "Var", "flags": ["is_initialized_in_class", "is_classmethod", "is_ready", "is_inferred"], "fullname": "pint.delegates.txt_defparser.context.Relation._from_string_and_context_sep", "name": "_from_string_and_context_sep", "type": {".class": "CallableType", "arg_kinds": [0, 0, 0, 0], "arg_names": ["cls", "s", "config", "separator"], "arg_types": [{".class": "TypeType", "item": "pint.delegates.txt_defparser.context.Relation"}, "builtins.str", "pint.delegates.base_defparser.ParserConfig", "builtins.str"], "bound_args": [], "def_extras": {"first_arg": "cls"}, "fallback": "builtins.function", "from_concatenate": false, "implicit": false, "is_ellipsis_args": false, "name": "_from_string_and_context_sep of Relation", "ret_type": {".class": "TypeAliasType", "args": ["pint.delegates.txt_defparser.context.Relation"], "type_ref": "pint._vendor.flexparser.FromString"}, "type_guard": null, "unpack_kwargs": false, "variables": []}}}}, "dst": {".class": "SymbolTableNode", "kind": "Mdef", "node": {".class": "Var", "flags": ["is_property", "is_ready"], "fullname": "pint.delegates.txt_defparser.context.Relation.dst", "name": "dst", "type": {".class": "AnyType", "missing_import_name": "pint.facets.context.definitions.UnitsContainer", "source_any": null, "type_of_any": 3}}}, "equation": {".class": "SymbolTableNode", "kind": "Mdef", "node": {".class": "Var", "flags": ["is_property", "is_ready"], "fullname": "pint.delegates.txt_defparser.context.Relation.equation", "name": "equation", "type": "builtins.str"}}, "src": {".class": "SymbolTableNode", "kind": "Mdef", "node": {".class": "Var", "flags": ["is_property", "is_ready"], "fullname": "pint.delegates.txt_defparser.context.Relation.src", "name": "src", "type": {".class": "AnyType", "missing_import_name": "pint.facets.context.definitions.UnitsContainer", "source_any": null, "type_of_any": 3}}}}, "self_type": null, "slots": null, "tuple_type": null, "type_vars": [], "typeddict_type": null}}, "Tuple": {".class": "SymbolTableNode", "cross_ref": "typing.Tuple", "kind": "Gdef"}, "__annotations__": {".class": "SymbolTableNode", "kind": "Gdef", "node": {".class": "Var", "flags": ["is_ready"], "fullname": "pint.delegates.txt_defparser.context.__annotations__", "name": "__annotations__", "type": {".class": "Instance", "args": ["builtins.str", {".class": "AnyType", "missing_import_name": null, "source_any": null, "type_of_any": 6}], "type_ref": "builtins.dict"}}}, "__doc__": {".class": "SymbolTableNode", "kind": "Gdef", "node": {".class": "Var", "flags": ["is_ready"], "fullname": "pint.delegates.txt_defparser.context.__doc__", "name": "__doc__", "type": "builtins.str"}}, "__file__": {".class": "SymbolTableNode", "kind": "Gdef", "node": {".class": "Var", "flags": ["is_ready"], "fullname": "pint.delegates.txt_defparser.context.__file__", "name": "__file__", "type": "builtins.str"}}, "__name__": {".class": "SymbolTableNode", "kind": "Gdef", "node": {".class": "Var", "flags": ["is_ready"], "fullname": "pint.delegates.txt_defparser.context.__name__", "name": "__name__", "type": "builtins.str"}}, "__package__": {".class": "SymbolTableNode", "kind": "Gdef", "node": {".class": "Var", "flags": ["is_ready"], "fullname": "pint.delegates.txt_defparser.context.__package__", "name": "__package__", "type": "builtins.str"}}, "annotations": {".class": "SymbolTableNode", "cross_ref": "__future__.annotations", "kind": "Gdef"}, "block": {".class": "SymbolTableNode", "cross_ref": "pint.delegates.txt_defparser.block", "kind": "Gdef"}, "common": {".class": "SymbolTableNode", "cross_ref": "pint.delegates.txt_defparser.common", "kind": "Gdef"}, "dataclass": {".class": "SymbolTableNode", "cross_ref": "dataclasses.dataclass", "kind": "Gdef"}, "definitions": {".class": "SymbolTableNode", "cross_ref": "pint.facets.context.definitions", "kind": "Gdef"}, "fp": {".class": "SymbolTableNode", "cross_ref": "pint._vendor.flexparser", "kind": "Gdef"}, "numbers": {".class": "SymbolTableNode", "cross_ref": "numbers", "kind": "Gdef"}, "plain": {".class": "SymbolTableNode", "cross_ref": "pint.delegates.txt_defparser.plain", "kind": "Gdef"}, "re": {".class": "SymbolTableNode", "cross_ref": "re", "kind": "Gdef"}, "ty": {".class": "SymbolTableNode", "cross_ref": "typing", "kind": "Gdef"}}, "path": "/Users/rtesse/.pyenv/versions/miniconda3-latest/envs/georges/lib/python3.10/site-packages/pint/delegates/txt_defparser/context.py"}